{
    "behavior_label": "Escalation_Path_To_Manager",
    "thread": [
        {
            "message_id": "msg_01",
            "reply_to_message_id": null,
            "day": 0,
            "time": "10:30",
            "sender": "partners@example.com",
            "recipient": "contact@crimsonpeakslodge.com",
            "cc": [],
            "subject": "Diwali Discount Offer for Partners",
            "body": "Dear Crimson Peaks Lodge Team,\n\nWe are writing to inquire about potential corporate rates for our Diwali partner event. We anticipate needing 20 Deluxe Rooms and 5 Suites for a 3-day stay from November 10th to 12th.  Could you please provide us with your best available rates and any applicable group discounts? We are particularly interested in utilizing your conference hall, 'The Grand Ballroom', for our event.\n\nThank you for your time and consideration.\n\nSincerely,\nRajesh Sharma\nLead Event Planner,  Example Corp"
        },
        {
            "message_id": "msg_02",
            "reply_to_message_id": "msg_01",
            "day": 0,
            "time": "10:45",
            "sender": "contact@crimsonpeakslodge.com",
            "recipient": "partners@example.com",
            "cc": [],
            "subject": "Re: Diwali Discount Offer for Partners",
            "body": "Dear Rajesh Sharma,\n\nThank you for your email.  Unfortunately, I am not authorized to handle corporate rate requests. I will forward this to our Sales Manager who can assist you with your inquiry.\n\nRegards,\nPriya Sharma\nFront Desk, Crimson Peaks Lodge"
        },
        {
            "message_id": "msg_03",
            "reply_to_message_id": "msg_01",
            "day": 0,
            "time": "14:15",
            "sender": "john.doe@crimsonpeakslodge.com",
            "recipient": "partners@example.com",
            "cc": [
                "contact@crimsonpeakslodge.com"
            ],
            "subject": "Re: Diwali Discount Offer for Partners",
            "body": "Dear Rajesh Sharma,\n\nThank you for your interest in Crimson Peaks Lodge for your Diwali event. I've received your request for corporate rates.  For your group of 25 rooms (20 Deluxe & 5 Suites) from November 10th-12th, and use of the Grand Ballroom, we can offer a special Diwali discount of 15% off our standard rates. This includes complimentary Wi-Fi and breakfast.\n\nTo confirm your booking and receive a detailed quote, please reply to this email.  We look forward to welcoming you to Crimson Peaks Lodge.\n\nSincerely,\nJohn Doe\nSales Manager, Crimson Peaks Lodge"
        },
        {
            "message_id": "msg_04",
            "reply_to_message_id": "msg_03",
            "day": 1,
            "time": "09:00",
            "sender": "partners@example.com",
            "recipient": "john.doe@crimsonpeakslodge.com",
            "cc": [],
            "subject": "Re: Diwali Discount Offer for Partners",
            "body": "Dear John,\n\nThank you for the prompt response and the attractive offer.  We would like to proceed with the booking.  Could you please send us a detailed quote with all inclusions and terms and conditions?\n\nRegards,\nRajesh Sharma"
        }
    ]
}